setup.py
funke_enrichment_core/__init__.py
funke_enrichment_core/control.py
funke_enrichment_core/helper.py
funke_enrichment_core/io.py
funke_enrichment_core.egg-info/PKG-INFO
funke_enrichment_core.egg-info/SOURCES.txt
funke_enrichment_core.egg-info/dependency_links.txt
funke_enrichment_core.egg-info/requires.txt
funke_enrichment_core.egg-info/top_level.txt