Metadata-Version: 2.1
Name: funke-enrichment-core
Version: 1.11.1
Summary: This package contains everthing to orchestrate several microservices in the GCP
Home-page: UNKNOWN
Author: Friedrich Schmidt
Author-email: friedrich.schmidt@funkemedien.de
License: MIT
Platform: UNKNOWN
